humanlens/__init__.py
humanlens/__main__.py
humanlens/core.py
humanlens/core_.py
humanlens/core_withRegistration.py
humanlens/rag.py
humanlens-0.1.5.dist-info/METADATA
humanlens-0.1.5.dist-info/WHEEL
humanlens-0.1.5.dist-info/entry_points.txt
humanlens-0.1.5.dist-info/top_level.txt
humanlens-0.1.5.dist-info/RECORD
