Metadata-Version: 2.4
Name: humanlens
Version: 0.1.5
Summary: A lightweight fairness and compliance auditing toolkit
Author-email: HumanLens <team@humanlens.ai>
Requires-Python: >=3.8
Requires-Dist: pandas>=1.5.0
Requires-Dist: numpy>=1.21.0
Requires-Dist: scikit-learn>=1.0
Requires-Dist: matplotlib>=3.5.0
Requires-Dist: seaborn>=0.11.0
Requires-Dist: fairlearn>=0.8.0
Requires-Dist: ipython
Provides-Extra: rag
Requires-Dist: ragas>=0.1.0; extra == "rag"
Requires-Dist: openai>=1.54.0; extra == "rag"
Requires-Dist: langchain>=0.2.0; extra == "rag"
Requires-Dist: langchain-openai>=0.2.0; extra == "rag"
Requires-Dist: tiktoken>=0.7.0; extra == "rag"
Provides-Extra: dev
Requires-Dist: pytest>=7.0; extra == "dev"
Requires-Dist: ruff>=0.5.0; extra == "dev"
Requires-Dist: black>=24.0.0; extra == "dev"
